mhi/xml/__init__.py
mhi/xml/__main__.py
mhi/xml/buildtime.py
mhi/xml/file.py
mhi/xml/mhi-xml.chm
mhi/xml/node.py
mhi/xml/py.typed
mhi/xml/types.py
mhi/xml/pscad/__init__.py
mhi/xml/pscad/_project.py
mhi/xml/pscad/colour.py
mhi/xml/pscad/component.py
mhi/xml/pscad/definition.py
mhi/xml/pscad/definitions.py
mhi/xml/pscad/graphics.py
mhi/xml/pscad/layer.py
mhi/xml/pscad/lookup.py
mhi/xml/pscad/project.py
mhi/xml/pscad/resource.py
mhi/xml/pscad/schematic.py
mhi/xml/pscad/substitution.py
mhi/xml/pscad/twm.py
mhi/xml/pscad/twm_types.py
mhi/xml/pscad/types.py
mhi/xml/pscad/vertex.py
mhi/xml/pscad/workspace.py
mhi_xml-1.2.1.dist-info/licenses/LICENSE
mhi_xml-1.2.1.dist-info/METADATA
mhi_xml-1.2.1.dist-info/WHEEL
mhi_xml-1.2.1.dist-info/top_level.txt
mhi_xml-1.2.1.dist-info/RECORD
