Metadata-Version: 2.4
Name: mhi-xml
Version: 1.2.1
Summary: Manitoba Hydro International: XML file updaters
Author-email: "Manitoba Hydro International Ltd." <pscad@mhi.ca>
License-Expression: BSD-3-Clause-Clear
Project-URL: Homepage, https://www.pscad.com/support/support-resources
Classifier: Development Status :: 2 - Pre-Alpha
Classifier: Programming Language :: Python :: 3
Classifier: Programming Language :: Python :: 3.9
Classifier: Programming Language :: Python :: 3.10
Classifier: Programming Language :: Python :: 3.11
Classifier: Programming Language :: Python :: 3.12
Classifier: Operating System :: Microsoft :: Windows
Requires-Python: >=3.9
License-File: LICENSE
Requires-Dist: lxml>=5.1.0
Provides-Extra: dev
Requires-Dist: coverage>=7.4.3; extra == "dev"
Requires-Dist: pytest>=8.0.1; extra == "dev"
Requires-Dist: pylint-gitlab>=2.0.0; extra == "dev"
Dynamic: license-file
